{
  "generated": "2026-06-07",
  "est_cost_usd": 1.2185,
  "results_collected": 85,
  "coverage": "52/53 queries desktop; breda via mobile; 11 other mobile timeouts (non-material)",
  "bm_top100": [
    {
      "q": "gevel sierpleister",
      "pos": 22,
      "url": "https://bm-klus-bv.nl/sierpleister/"
    },
    {
      "q": "sausklaar stucen",
      "pos": 24,
      "url": "https://bm-klus-bv.nl/muren-stucen/"
    },
    {
      "q": "behangklaar stucen",
      "pos": 38,
      "url": "https://bm-klus-bv.nl/muren-stucen/"
    },
    {
      "q": "gevel schilderen kosten",
      "pos": 25,
      "url": "https://bm-klus-bv.nl/gevel-schilderen/"
    }
  ],
  "serp_feature_freq_desktop": {
    "related_searches": 450,
    "images": 150,
    "local_pack": 132,
    "popular_products": 58,
    "people_also_ask": 43,
    "people_also_search": 34,
    "video": 23,
    "ai_overview": 22,
    "featured_snippet": 4,
    "short_videos": 4
  },
  "final_cost_usd": 1.3565,
  "results_ok": 94,
  "timeouts": 12
}